azure/mgmt/secretsstoreextension/__init__.py
azure/mgmt/secretsstoreextension/_client.py
azure/mgmt/secretsstoreextension/_configuration.py
azure/mgmt/secretsstoreextension/_patch.py
azure/mgmt/secretsstoreextension/_version.py
azure/mgmt/secretsstoreextension/py.typed
azure/mgmt/secretsstoreextension/_utils/__init__.py
azure/mgmt/secretsstoreextension/_utils/model_base.py
azure/mgmt/secretsstoreextension/_utils/serialization.py
azure/mgmt/secretsstoreextension/aio/__init__.py
azure/mgmt/secretsstoreextension/aio/_client.py
azure/mgmt/secretsstoreextension/aio/_configuration.py
azure/mgmt/secretsstoreextension/aio/_patch.py
azure/mgmt/secretsstoreextension/aio/operations/__init__.py
azure/mgmt/secretsstoreextension/aio/operations/_operations.py
azure/mgmt/secretsstoreextension/aio/operations/_patch.py
azure/mgmt/secretsstoreextension/models/__init__.py
azure/mgmt/secretsstoreextension/models/_enums.py
azure/mgmt/secretsstoreextension/models/_models.py
azure/mgmt/secretsstoreextension/models/_patch.py
azure/mgmt/secretsstoreextension/operations/__init__.py
azure/mgmt/secretsstoreextension/operations/_operations.py
azure/mgmt/secretsstoreextension/operations/_patch.py
azure_mgmt_secretsstoreextension-1.0.0b1.dist-info/LICENSE
azure_mgmt_secretsstoreextension-1.0.0b1.dist-info/METADATA
azure_mgmt_secretsstoreextension-1.0.0b1.dist-info/WHEEL
azure_mgmt_secretsstoreextension-1.0.0b1.dist-info/top_level.txt
azure_mgmt_secretsstoreextension-1.0.0b1.dist-info/RECORD
